easyaspyplotting/__init__.py
easyaspyplotting/themes.py
easyaspyplotting-0.0.2.dist-info/METADATA
easyaspyplotting-0.0.2.dist-info/WHEEL
easyaspyplotting-0.0.2.dist-info/top_level.txt
easyaspyplotting-0.0.2.dist-info/RECORD
