Metadata-Version: 2.1
Name: easyaspyplotting
Version: 0.0.2
Summary: A small
Home-page: https://github.com/selkamand/easyaspyplotting
Author: selkamand
Author-email: sam.elkamand@gmail.com
License: UNKNOWN
Project-URL: Bug Tracker, https://github.com/selkamand/easyaspyplotting/issues
Platform: UNKNOWN
Classifier: Programming Language :: Python :: 3
Classifier: License :: OSI Approved :: MIT License
Classifier: Operating System :: OS Independent
Requires-Python: >=3.6
Requires-Dist: matplotlib
Requires-Dist: seaborn
